[{"iob":2.016,"activity":0.0123,"bolussnooze":1.7,"basaliob":0.089,"netbasalinsulin":0.25,"hightempinsulin":0.75,"time":"2017-04-18T19:47:35.000Z"},{"iob":1.95,"activity":0.0132,"bolussnooze":1.551,"basaliob":0.067,"netbasalinsulin":0.3,"hightempinsulin":0.75,"time":"2017-04-18T19:52:35.000Z"},{"iob":1.88,"activity":0.014,"bolussnooze":1.373,"basaliob":0.047,"netbasalinsulin":0.4,"hightempinsulin":0.75,"time":"2017-04-18T19:57:35.000Z"},{"iob":1.806,"activity":0.0147,"bolussnooze":1.165,"basaliob":0.028,"netbasalinsulin":0.45,"hightempinsulin":0.75,"time":"2017-04-18T20:02:35.000Z"},{"iob":1.729,"activity":0.0155,"bolussnooze":0.952,"basaliob":0.012,"netbasalinsulin":0.5,"hightempinsulin":0.75,"time":"2017-04-18T20:07:35.000Z"},{"iob":1.646,"activity":0.0165,"bolussnooze":0.762,"basaliob":-0.002,"netbasalinsulin":0.55,"hightempinsulin":0.75,"time":"2017-04-18T20:12:35.000Z"},{"iob":1.559,"activity":0.0175,"bolussnooze":0.593,"basaliob":-0.014,"netbasalinsulin":0.6,"hightempinsulin":0.75,"time":"2017-04-18T20:17:35.000Z"},{"iob":1.466,"activity":0.0185,"bolussnooze":0.445,"basaliob":-0.022,"netbasalinsulin":0.6,"hightempinsulin":0.75,"time":"2017-04-18T20:22:35.000Z"},{"iob":1.369,"activity":0.0195,"bolussnooze":0.318,"basaliob":-0.029,"netbasalinsulin":0.6,"hightempinsulin":0.75,"time":"2017-04-18T20:27:35.000Z"},{"iob":1.266,"activity":0.0205,"bolussnooze":0.213,"basaliob":-0.033,"netbasalinsulin":0.55,"hightempinsulin":0.7,"time":"2017-04-18T20:32:35.000Z"},{"iob":1.158,"activity":0.0216,"bolussnooze":0.128,"basaliob":-0.036,"netbasalinsulin":0.5,"hightempinsulin":0.65,"time":"2017-04-18T20:37:35.000Z"},{"iob":1.046,"activity":0.0222,"bolussnooze":0.065,"basaliob":-0.037,"netbasalinsulin":0.45,"hightempinsulin":0.6,"time":"2017-04-18T20:42:35.000Z"},{"iob":0.942,"activity":0.0209,"bolussnooze":0.023,"basaliob":-0.037,"netbasalinsulin":0.35,"hightempinsulin":0.5,"time":"2017-04-18T20:47:35.000Z"},{"iob":0.844,"activity":0.0197,"bolussnooze":0.002,"basaliob":-0.036,"netbasalinsulin":0.3,"hightempinsulin":0.45,"time":"2017-04-18T20:52:35.000Z"},{"iob":0.751,"activity":0.0185,"bolussnooze":0,"basaliob":-0.034,"netbasalinsulin":0.2,"hightempinsulin":0.35,"time":"2017-04-18T20:57:35.000Z"},{"iob":0.665,"activity":0.0173,"bolussnooze":0,"basaliob":-0.032,"netbasalinsulin":0.2,"hightempinsulin":0.35,"time":"2017-04-18T21:02:35.000Z"},{"iob":0.584,"activity":0.0162,"bolussnooze":0,"basaliob":-0.03,"netbasalinsulin":0.15,"hightempinsulin":0.3,"time":"2017-04-18T21:07:35.000Z"},{"iob":0.509,"activity":0.015,"bolussnooze":0,"basaliob":-0.027,"netbasalinsulin":0.1,"hightempinsulin":0.25,"time":"2017-04-18T21:12:35.000Z"},{"iob":0.439,"activity":0.0139,"bolussnooze":0,"basaliob":-0.024,"netbasalinsulin":0.05,"hightempinsulin":0.2,"time":"2017-04-18T21:17:35.000Z"},{"iob":0.375,"activity":0.0129,"bolussnooze":0,"basaliob":-0.021,"netbasalinsulin":0.05,"hightempinsulin":0.2,"time":"2017-04-18T21:22:35.000Z"},{"iob":0.316,"activity":0.0118,"bolussnooze":0,"basaliob":-0.018,"netbasalinsulin":-0.05,"hightempinsulin":0.1,"time":"2017-04-18T21:27:35.000Z"},{"iob":0.262,"activity":0.0108,"bolussnooze":0,"basaliob":-0.015,"netbasalinsulin":-0.05,"hightempinsulin":0.1,"time":"2017-04-18T21:32:35.000Z"},{"iob":0.213,"activity":0.0097,"bolussnooze":0,"basaliob":-0.012,"netbasalinsulin":-0.05,"hightempinsulin":0.1,"time":"2017-04-18T21:37:35.000Z"},{"iob":0.17,"activity":0.0087,"bolussnooze":0,"basaliob":-0.009,"netbasalinsulin":-0.05,"hightempinsulin":0.1,"time":"2017-04-18T21:42:35.000Z"},{"iob":0.131,"activity":0.0077,"bolussnooze":0,"basaliob":-0.007,"netbasalinsulin":-0.1,"hightempinsulin":0.05,"time":"2017-04-18T21:47:35.000Z"},{"iob":0.098,"activity":0.0067,"bolussnooze":0,"basaliob":-0.005,"netbasalinsulin":-0.15,"hightempinsulin":0,"time":"2017-04-18T21:52:35.000Z"},{"iob":0.069,"activity":0.0057,"bolussnooze":0,"basaliob":-0.003,"netbasalinsulin":-0.15,"hightempinsulin":0,"time":"2017-04-18T21:57:35.000Z"},{"iob":0.045,"activity":0.0048,"bolussnooze":0,"basaliob":-0.002,"netbasalinsulin":-0.15,"hightempinsulin":0,"time":"2017-04-18T22:02:35.000Z"},{"iob":0.026,"activity":0.0038,"bolussnooze":0,"basaliob":-0.001,"netbasalinsulin":-0.15,"hightempinsulin":0,"time":"2017-04-18T22:07:35.000Z"},{"iob":0.012,"activity":0.0028,"bolussnooze":0,"basaliob":0,"netbasalinsulin":-0.15,"hightempinsulin":0,"time":"2017-04-18T22:12:35.000Z"},{"iob":0.004,"activity":0.0018,"bolussnooze":0,"basaliob":0,"netbasalinsulin":-0.1,"hightempinsulin":0,"time":"2017-04-18T22:17:35.000Z"},{"iob":0,"activity":0.0008,"bolussnooze":0,"basaliob":0,"netbasalinsulin":-0.05,"hightempinsulin":0,"time":"2017-04-18T22:22:35.000Z"},{"iob":0,"activity":0,"bolussnooze":0,"basaliob":0,"netbasalinsulin":0,"hightempinsulin":0,"time":"2017-04-18T22:27:35.000Z"},{"iob":0,"activity":0,"bolussnooze":0,"basaliob":0,"netbasalinsulin":0,"hightempinsulin":0,"time":"2017-04-18T22:32:35.000Z"},{"iob":0,"activity":0,"bolussnooze":0,"basaliob":0,"netbasalinsulin":0,"hightempinsulin":0,"time":"2017-04-18T22:37:35.000Z"},{"iob":0,"activity":0,"bolussnooze":0,"basaliob":0,"netbasalinsulin":0,"hightempinsulin":0,"time":"2017-04-18T22:42:35.000Z"},{"iob":0,"activity":0,"bolussnooze":0,"basaliob":0,"netbasalinsulin":0,"hightempinsulin":0,"time":"2017-04-18T22:47:35.000Z"},{"iob":0,"activity":0,"bolussnooze":0,"basaliob":0,"netbasalinsulin":0,"hightempinsulin":0,"time":"2017-04-18T22:52:35.000Z"},{"iob":0,"activity":0,"bolussnooze":0,"basaliob":0,"netbasalinsulin":0,"hightempinsulin":0,"time":"2017-04-18T22:57:35.000Z"},{"iob":0,"activity":0,"bolussnooze":0,"basaliob":0,"netbasalinsulin":0,"hightempinsulin":0,"time":"2017-04-18T23:02:35.000Z"},{"iob":0,"activity":0,"bolussnooze":0,"basaliob":0,"netbasalinsulin":0,"hightempinsulin":0,"time":"2017-04-18T23:07:35.000Z"},{"iob":0,"activity":0,"bolussnooze":0,"basaliob":0,"netbasalinsulin":0,"hightempinsulin":0,"time":"2017-04-18T23:12:35.000Z"}]
