[{"iob":1.508,"activity":0.0298,"bolussnooze":0,"basaliob":0.362,"netbasalinsulin":0.2,"hightempinsulin":0.55,"time":"2017-04-09T01:59:15.000Z"},{"iob":1.416,"activity":0.0285,"bolussnooze":0,"basaliob":0.403,"netbasalinsulin":0.3,"hightempinsulin":0.6,"time":"2017-04-09T02:04:15.000Z"},{"iob":1.38,"activity":0.0272,"bolussnooze":0,"basaliob":0.492,"netbasalinsulin":0.4,"hightempinsulin":0.7,"time":"2017-04-09T02:09:15.000Z"},{"iob":1.3,"activity":0.0259,"bolussnooze":0,"basaliob":0.529,"netbasalinsulin":0.5,"hightempinsulin":0.75,"time":"2017-04-09T02:14:15.000Z"},{"iob":1.227,"activity":0.0247,"bolussnooze":0,"basaliob":0.564,"netbasalinsulin":0.6,"hightempinsulin":0.8,"time":"2017-04-09T02:19:15.000Z"},{"iob":1.21,"activity":0.0235,"bolussnooze":0,"basaliob":0.646,"netbasalinsulin":0.75,"hightempinsulin":0.9,"time":"2017-04-09T02:24:15.000Z"},{"iob":1.098,"activity":0.0224,"bolussnooze":0,"basaliob":0.626,"netbasalinsulin":0.8,"hightempinsulin":0.9,"time":"2017-04-09T02:29:15.000Z"},{"iob":0.992,"activity":0.0212,"bolussnooze":0,"basaliob":0.604,"netbasalinsulin":0.85,"hightempinsulin":0.9,"time":"2017-04-09T02:34:15.000Z"},{"iob":0.892,"activity":0.02,"bolussnooze":0,"basaliob":0.58,"netbasalinsulin":0.85,"hightempinsulin":0.9,"time":"2017-04-09T02:39:15.000Z"},{"iob":0.798,"activity":0.0187,"bolussnooze":0,"basaliob":0.554,"netbasalinsulin":0.85,"hightempinsulin":0.9,"time":"2017-04-09T02:44:15.000Z"},{"iob":0.711,"activity":0.0174,"bolussnooze":0,"basaliob":0.526,"netbasalinsulin":0.85,"hightempinsulin":0.9,"time":"2017-04-09T02:49:15.000Z"},{"iob":0.631,"activity":0.0161,"bolussnooze":0,"basaliob":0.496,"netbasalinsulin":0.85,"hightempinsulin":0.9,"time":"2017-04-09T02:54:15.000Z"},{"iob":0.558,"activity":0.0147,"bolussnooze":0,"basaliob":0.466,"netbasalinsulin":0.85,"hightempinsulin":0.9,"time":"2017-04-09T02:59:15.000Z"},{"iob":0.492,"activity":0.0132,"bolussnooze":0,"basaliob":0.434,"netbasalinsulin":0.85,"hightempinsulin":0.9,"time":"2017-04-09T03:04:15.000Z"},{"iob":0.434,"activity":0.0116,"bolussnooze":0,"basaliob":0.402,"netbasalinsulin":0.85,"hightempinsulin":0.9,"time":"2017-04-09T03:09:15.000Z"},{"iob":0.384,"activity":0.01,"bolussnooze":0,"basaliob":0.37,"netbasalinsulin":0.85,"hightempinsulin":0.9,"time":"2017-04-09T03:14:15.000Z"},{"iob":0.342,"activity":0.0084,"bolussnooze":0,"basaliob":0.339,"netbasalinsulin":0.75,"hightempinsulin":0.8,"time":"2017-04-09T03:19:15.000Z"},{"iob":0.307,"activity":0.007,"bolussnooze":0,"basaliob":0.307,"netbasalinsulin":0.7,"hightempinsulin":0.75,"time":"2017-04-09T03:24:15.000Z"},{"iob":0.277,"activity":0.0061,"bolussnooze":0,"basaliob":0.277,"netbasalinsulin":0.65,"hightempinsulin":0.7,"time":"2017-04-09T03:29:15.000Z"},{"iob":0.247,"activity":0.0059,"bolussnooze":0,"basaliob":0.247,"netbasalinsulin":0.65,"hightempinsulin":0.7,"time":"2017-04-09T03:34:15.000Z"},{"iob":0.219,"activity":0.0056,"bolussnooze":0,"basaliob":0.219,"netbasalinsulin":0.65,"hightempinsulin":0.7,"time":"2017-04-09T03:39:15.000Z"},{"iob":0.192,"activity":0.0053,"bolussnooze":0,"basaliob":0.192,"netbasalinsulin":0.65,"hightempinsulin":0.7,"time":"2017-04-09T03:44:15.000Z"},{"iob":0.168,"activity":0.0049,"bolussnooze":0,"basaliob":0.168,"netbasalinsulin":0.65,"hightempinsulin":0.7,"time":"2017-04-09T03:49:15.000Z"},{"iob":0.145,"activity":0.0046,"bolussnooze":0,"basaliob":0.145,"netbasalinsulin":0.65,"hightempinsulin":0.7,"time":"2017-04-09T03:54:15.000Z"},{"iob":0.123,"activity":0.0043,"bolussnooze":0,"basaliob":0.123,"netbasalinsulin":0.65,"hightempinsulin":0.7,"time":"2017-04-09T03:59:15.000Z"},{"iob":0.104,"activity":0.0039,"bolussnooze":0,"basaliob":0.104,"netbasalinsulin":0.7,"hightempinsulin":0.7,"time":"2017-04-09T04:04:15.000Z"},{"iob":0.086,"activity":0.0035,"bolussnooze":0,"basaliob":0.086,"netbasalinsulin":0.7,"hightempinsulin":0.7,"time":"2017-04-09T04:09:15.000Z"},{"iob":0.071,"activity":0.0032,"bolussnooze":0,"basaliob":0.071,"netbasalinsulin":0.7,"hightempinsulin":0.7,"time":"2017-04-09T04:14:15.000Z"},{"iob":0.057,"activity":0.0028,"bolussnooze":0,"basaliob":0.057,"netbasalinsulin":0.7,"hightempinsulin":0.7,"time":"2017-04-09T04:19:15.000Z"},{"iob":0.045,"activity":0.0024,"bolussnooze":0,"basaliob":0.045,"netbasalinsulin":0.7,"hightempinsulin":0.7,"time":"2017-04-09T04:24:15.000Z"},{"iob":0.034,"activity":0.0021,"bolussnooze":0,"basaliob":0.034,"netbasalinsulin":0.65,"hightempinsulin":0.65,"time":"2017-04-09T04:29:15.000Z"},{"iob":0.026,"activity":0.0017,"bolussnooze":0,"basaliob":0.026,"netbasalinsulin":0.6,"hightempinsulin":0.6,"time":"2017-04-09T04:34:15.000Z"},{"iob":0.019,"activity":0.0014,"bolussnooze":0,"basaliob":0.019,"netbasalinsulin":0.55,"hightempinsulin":0.55,"time":"2017-04-09T04:39:15.000Z"},{"iob":0.013,"activity":0.0011,"bolussnooze":0,"basaliob":0.013,"netbasalinsulin":0.5,"hightempinsulin":0.5,"time":"2017-04-09T04:44:15.000Z"},{"iob":0.009,"activity":0.0009,"bolussnooze":0,"basaliob":0.009,"netbasalinsulin":0.45,"hightempinsulin":0.45,"time":"2017-04-09T04:49:15.000Z"},{"iob":0.005,"activity":0.0007,"bolussnooze":0,"basaliob":0.005,"netbasalinsulin":0.4,"hightempinsulin":0.4,"time":"2017-04-09T04:54:15.000Z"},{"iob":0.003,"activity":0.0005,"bolussnooze":0,"basaliob":0.003,"netbasalinsulin":0.35,"hightempinsulin":0.35,"time":"2017-04-09T04:59:15.000Z"},{"iob":0.001,"activity":0.0003,"bolussnooze":0,"basaliob":0.001,"netbasalinsulin":0.3,"hightempinsulin":0.3,"time":"2017-04-09T05:04:15.000Z"},{"iob":0,"activity":0.0002,"bolussnooze":0,"basaliob":0,"netbasalinsulin":0.2,"hightempinsulin":0.2,"time":"2017-04-09T05:09:15.000Z"},{"iob":0,"activity":0.0001,"bolussnooze":0,"basaliob":0,"netbasalinsulin":0.15,"hightempinsulin":0.15,"time":"2017-04-09T05:14:15.000Z"},{"iob":0,"activity":0,"bolussnooze":0,"basaliob":0,"netbasalinsulin":0.1,"hightempinsulin":0.1,"time":"2017-04-09T05:19:15.000Z"},{"iob":0,"activity":0,"bolussnooze":0,"basaliob":0,"netbasalinsulin":0,"hightempinsulin":0,"time":"2017-04-09T05:24:15.000Z"}]
