[{"iob":1.615,"activity":0.026,"bolussnooze":0,"basaliob":1.615,"netbasalinsulin":3.15,"hightempinsulin":3.2,"time":"2017-03-29T22:11:47.000Z"},{"iob":1.536,"activity":0.0259,"bolussnooze":0,"basaliob":1.536,"netbasalinsulin":3.2,"hightempinsulin":3.25,"time":"2017-03-29T22:16:47.000Z"},{"iob":1.458,"activity":0.0254,"bolussnooze":0,"basaliob":1.458,"netbasalinsulin":3.25,"hightempinsulin":3.3,"time":"2017-03-29T22:21:47.000Z"},{"iob":1.334,"activity":0.0248,"bolussnooze":0,"basaliob":1.334,"netbasalinsulin":3.25,"hightempinsulin":3.3,"time":"2017-03-29T22:26:47.000Z"},{"iob":1.214,"activity":0.024,"bolussnooze":0,"basaliob":1.214,"netbasalinsulin":3.3,"hightempinsulin":3.3,"time":"2017-03-29T22:31:47.000Z"},{"iob":1.098,"activity":0.0231,"bolussnooze":0,"basaliob":1.098,"netbasalinsulin":3.3,"hightempinsulin":3.3,"time":"2017-03-29T22:36:47.000Z"},{"iob":0.988,"activity":0.0221,"bolussnooze":0,"basaliob":0.988,"netbasalinsulin":3.3,"hightempinsulin":3.3,"time":"2017-03-29T22:41:47.000Z"},{"iob":0.883,"activity":0.021,"bolussnooze":0,"basaliob":0.883,"netbasalinsulin":3.3,"hightempinsulin":3.3,"time":"2017-03-29T22:46:47.000Z"},{"iob":0.784,"activity":0.0198,"bolussnooze":0,"basaliob":0.784,"netbasalinsulin":3.3,"hightempinsulin":3.3,"time":"2017-03-29T22:51:47.000Z"},{"iob":0.691,"activity":0.0184,"bolussnooze":0,"basaliob":0.691,"netbasalinsulin":3.3,"hightempinsulin":3.3,"time":"2017-03-29T22:56:47.000Z"},{"iob":0.606,"activity":0.017,"bolussnooze":0,"basaliob":0.606,"netbasalinsulin":3.3,"hightempinsulin":3.3,"time":"2017-03-29T23:01:47.000Z"},{"iob":0.528,"activity":0.0156,"bolussnooze":0,"basaliob":0.528,"netbasalinsulin":3.2,"hightempinsulin":3.2,"time":"2017-03-29T23:06:47.000Z"},{"iob":0.457,"activity":0.0142,"bolussnooze":0,"basaliob":0.457,"netbasalinsulin":3.15,"hightempinsulin":3.15,"time":"2017-03-29T23:11:47.000Z"},{"iob":0.393,"activity":0.0129,"bolussnooze":0,"basaliob":0.393,"netbasalinsulin":3,"hightempinsulin":3,"time":"2017-03-29T23:16:47.000Z"},{"iob":0.335,"activity":0.0115,"bolussnooze":0,"basaliob":0.335,"netbasalinsulin":2.85,"hightempinsulin":2.85,"time":"2017-03-29T23:21:47.000Z"},{"iob":0.284,"activity":0.0102,"bolussnooze":0,"basaliob":0.284,"netbasalinsulin":2.65,"hightempinsulin":2.65,"time":"2017-03-29T23:26:47.000Z"},{"iob":0.239,"activity":0.009,"bolussnooze":0,"basaliob":0.239,"netbasalinsulin":2.4,"hightempinsulin":2.4,"time":"2017-03-29T23:31:47.000Z"},{"iob":0.2,"activity":0.0078,"bolussnooze":0,"basaliob":0.2,"netbasalinsulin":2.2,"hightempinsulin":2.2,"time":"2017-03-29T23:36:47.000Z"},{"iob":0.166,"activity":0.0068,"bolussnooze":0,"basaliob":0.166,"netbasalinsulin":1.95,"hightempinsulin":1.95,"time":"2017-03-29T23:41:47.000Z"},{"iob":0.138,"activity":0.0058,"bolussnooze":0,"basaliob":0.138,"netbasalinsulin":1.75,"hightempinsulin":1.75,"time":"2017-03-29T23:46:47.000Z"},{"iob":0.113,"activity":0.0049,"bolussnooze":0,"basaliob":0.113,"netbasalinsulin":1.55,"hightempinsulin":1.55,"time":"2017-03-29T23:51:47.000Z"},{"iob":0.093,"activity":0.0041,"bolussnooze":0,"basaliob":0.093,"netbasalinsulin":1.4,"hightempinsulin":1.4,"time":"2017-03-29T23:56:47.000Z"},{"iob":0.075,"activity":0.0035,"bolussnooze":0,"basaliob":0.075,"netbasalinsulin":1.15,"hightempinsulin":1.15,"time":"2017-03-30T00:01:47.000Z"},{"iob":0.061,"activity":0.0029,"bolussnooze":0,"basaliob":0.061,"netbasalinsulin":0.95,"hightempinsulin":0.95,"time":"2017-03-30T00:06:47.000Z"},{"iob":0.049,"activity":0.0024,"bolussnooze":0,"basaliob":0.049,"netbasalinsulin":0.8,"hightempinsulin":0.8,"time":"2017-03-30T00:11:47.000Z"},{"iob":0.038,"activity":0.002,"bolussnooze":0,"basaliob":0.038,"netbasalinsulin":0.7,"hightempinsulin":0.7,"time":"2017-03-30T00:16:47.000Z"},{"iob":0.03,"activity":0.0017,"bolussnooze":0,"basaliob":0.03,"netbasalinsulin":0.6,"hightempinsulin":0.6,"time":"2017-03-30T00:21:47.000Z"},{"iob":0.023,"activity":0.0014,"bolussnooze":0,"basaliob":0.023,"netbasalinsulin":0.55,"hightempinsulin":0.55,"time":"2017-03-30T00:26:47.000Z"},{"iob":0.018,"activity":0.0011,"bolussnooze":0,"basaliob":0.018,"netbasalinsulin":0.45,"hightempinsulin":0.45,"time":"2017-03-30T00:31:47.000Z"},{"iob":0.013,"activity":0.0009,"bolussnooze":0,"basaliob":0.013,"netbasalinsulin":0.35,"hightempinsulin":0.35,"time":"2017-03-30T00:36:47.000Z"},{"iob":0.009,"activity":0.0007,"bolussnooze":0,"basaliob":0.009,"netbasalinsulin":0.25,"hightempinsulin":0.25,"time":"2017-03-30T00:41:47.000Z"},{"iob":0.006,"activity":0.0006,"bolussnooze":0,"basaliob":0.006,"netbasalinsulin":0.25,"hightempinsulin":0.25,"time":"2017-03-30T00:46:47.000Z"},{"iob":0.004,"activity":0.0005,"bolussnooze":0,"basaliob":0.004,"netbasalinsulin":0.25,"hightempinsulin":0.25,"time":"2017-03-30T00:51:47.000Z"},{"iob":0.002,"activity":0.0003,"bolussnooze":0,"basaliob":0.002,"netbasalinsulin":0.25,"hightempinsulin":0.25,"time":"2017-03-30T00:56:47.000Z"},{"iob":0.001,"activity":0.0002,"bolussnooze":0,"basaliob":0.001,"netbasalinsulin":0.2,"hightempinsulin":0.2,"time":"2017-03-30T01:01:47.000Z"},{"iob":0,"activity":0.0001,"bolussnooze":0,"basaliob":0,"netbasalinsulin":0.15,"hightempinsulin":0.15,"time":"2017-03-30T01:06:47.000Z"},{"iob":0,"activity":0.0001,"bolussnooze":0,"basaliob":0,"netbasalinsulin":0.1,"hightempinsulin":0.1,"time":"2017-03-30T01:11:47.000Z"},{"iob":0,"activity":0,"bolussnooze":0,"basaliob":0,"netbasalinsulin":0.05,"hightempinsulin":0.05,"time":"2017-03-30T01:16:47.000Z"},{"iob":0,"activity":0,"bolussnooze":0,"basaliob":0,"netbasalinsulin":0,"hightempinsulin":0,"time":"2017-03-30T01:21:47.000Z"},{"iob":0,"activity":0,"bolussnooze":0,"basaliob":0,"netbasalinsulin":0,"hightempinsulin":0,"time":"2017-03-30T01:26:47.000Z"},{"iob":0,"activity":0,"bolussnooze":0,"basaliob":0,"netbasalinsulin":0,"hightempinsulin":0,"time":"2017-03-30T01:31:47.000Z"},{"iob":0,"activity":0,"bolussnooze":0,"basaliob":0,"netbasalinsulin":0,"hightempinsulin":0,"time":"2017-03-30T01:36:47.000Z"}]
