{
  "bg": 111, 
  "temp": "absolute", 
  "snoozeBG": 91, 
  "predBGs": {
    "IOB": [
      111, 
      107, 
      104, 
      100, 
      97, 
      94, 
      92, 
      89, 
      88, 
      86, 
      85, 
      84, 
      84, 
      83, 
      83, 
      84, 
      84, 
      84, 
      85, 
      86, 
      87, 
      88, 
      89, 
      90, 
      91, 
      92, 
      93, 
      93, 
      94, 
      95, 
      95, 
      95, 
      96
    ]
  }, 
  "reason": "COB: 0, Dev: -5, BGI: -3.07, ISF: 86, Target: 96; Eventual BG 90 < 96, temp 0 ~< req 0.55U/hr", 
  "COB": 0, 
  "eventualBG": 90, 
  "tick": -3, 
  "IOB": 0.185
}