{
  "bg": 163, 
  "temp": "absolute", 
  "snoozeBG": 144, 
  "predBGs": {
    "IOB": [
      163, 
      160, 
      156, 
      153, 
      150, 
      148, 
      145, 
      143, 
      142, 
      140, 
      139, 
      137, 
      136, 
      135, 
      135, 
      134, 
      134, 
      134, 
      134, 
      134, 
      135, 
      135, 
      135, 
      136, 
      136, 
      137, 
      137, 
      137, 
      137, 
      138, 
      138, 
      138, 
      138, 
      137
    ]
  }, 
  "reason": "COB: 0, Dev: 15, BGI: -5.73, ISF: 103, Target: 103; Eventual BG 144 >= 103, temp 1.55<1.7U/hr, but 30m left and 1.55 ~ req 1.7U/hr: no action required", 
  "COB": 0, 
  "eventualBG": 144, 
  "tick": -1, 
  "IOB": 0.329
}