{
  "bg": 130, 
  "temp": "absolute", 
  "snoozeBG": 147, 
  "predBGs": {
    "COB": [
      130, 
      131, 
      132, 
      134, 
      136, 
      138, 
      141, 
      143, 
      145, 
      147, 
      148, 
      149, 
      150, 
      151, 
      152, 
      154, 
      155, 
      156, 
      158, 
      160, 
      162, 
      164, 
      167, 
      170, 
      173, 
      177, 
      180, 
      184, 
      189, 
      193, 
      198, 
      203, 
      208, 
      213, 
      219, 
      224, 
      230, 
      236, 
      242, 
      248, 
      254, 
      259, 
      265
    ], 
    "aCOB": [
      130, 
      132, 
      134, 
      137, 
      140, 
      143, 
      146, 
      149, 
      152, 
      154, 
      156, 
      158, 
      160, 
      162, 
      163, 
      165, 
      167, 
      169, 
      171, 
      174, 
      176, 
      179, 
      183, 
      186, 
      190, 
      194, 
      198, 
      202, 
      207, 
      212, 
      217, 
      222, 
      228, 
      233, 
      239, 
      245, 
      251, 
      258, 
      264, 
      270, 
      276, 
      282, 
      288
    ], 
    "IOB": [
      130, 
      130, 
      130, 
      130, 
      129, 
      128, 
      127, 
      124, 
      121, 
      116, 
      111, 
      105, 
      98, 
      91, 
      84, 
      77, 
      70, 
      64, 
      58, 
      52, 
      47, 
      42, 
      39
    ]
  }, 
  "reason": "COB: 58, Dev: 55, BGI: -8.12, ISF: 95, Target: 100; Eventual BG 265 >= 100, temp 2.5 >~ req 1.6U/hr", 
  "COB": 58, 
  "eventualBG": 265, 
  "tick": "+1", 
  "IOB": 1.194
}