{
  "bg": 117, 
  "temp": "absolute", 
  "snoozeBG": 85, 
  "predBGs": {
    "COB": [
      117, 
      115, 
      112, 
      110, 
      108, 
      106, 
      103, 
      101, 
      99, 
      97, 
      95, 
      93, 
      92, 
      90, 
      89, 
      87, 
      86, 
      86, 
      85, 
      85, 
      86, 
      86, 
      87, 
      88, 
      89, 
      89, 
      90, 
      92, 
      93, 
      94, 
      95, 
      97, 
      98, 
      100, 
      102, 
      103, 
      105, 
      107, 
      108, 
      110, 
      111, 
      113, 
      114
    ], 
    "aCOB": [
      117, 
      120, 
      123, 
      126, 
      129, 
      131, 
      133, 
      134, 
      136, 
      137, 
      138, 
      138, 
      139, 
      139, 
      139, 
      139, 
      139, 
      139, 
      139, 
      139, 
      139, 
      139, 
      138, 
      138, 
      137, 
      136, 
      135, 
      133, 
      132, 
      131, 
      131, 
      130, 
      129, 
      129, 
      129, 
      128
    ], 
    "IOB": [
      117, 
      114, 
      111, 
      108, 
      105, 
      101, 
      98, 
      94, 
      89, 
      85, 
      80, 
      75, 
      70, 
      65, 
      61, 
      57, 
      53, 
      49, 
      46, 
      43, 
      41, 
      39
    ]
  }, 
  "rate": 0.625, 
  "reason": "COB: 10, Dev: 2, BGI: -6.41, ISF: 95, Target: 100; Eventual BG 114 > 100 but Min. Delta -6.00 < Exp. Delta -2.4; setting current basal of 0.625 as temp. Setting neutral temp basal of 0.625U/hr", 
  "COB": 10, 
  "eventualBG": 114, 
  "duration": 30, 
  "tick": -6, 
  "IOB": 0.956
}