{
  "bg": 99, 
  "temp": "absolute", 
  "snoozeBG": 18, 
  "predBGs": {
    "COB": [
      99, 
      89, 
      80, 
      72, 
      63, 
      56, 
      49, 
      43, 
      39, 
      39, 
      39, 
      39, 
      39
    ], 
    "aCOB": [
      99, 
      99, 
      99, 
      99, 
      100, 
      101, 
      102, 
      104, 
      107, 
      111, 
      115, 
      119, 
      123, 
      128, 
      132, 
      137, 
      143, 
      148, 
      153, 
      159, 
      164, 
      170, 
      175, 
      181, 
      186, 
      191, 
      196, 
      201, 
      206, 
      210, 
      214, 
      217, 
      221, 
      224, 
      227, 
      229, 
      232, 
      234, 
      235, 
      237, 
      238, 
      239, 
      240
    ], 
    "IOB": [
      99, 
      89, 
      80, 
      71, 
      63, 
      55, 
      48, 
      42, 
      39, 
      39, 
      39, 
      39, 
      39
    ]
  }, 
  "rate": 0, 
  "reason": "COB: 28, Dev: 2, BGI: -9.94, ISF: 88, Target: 97; Eventual BG 39 < 97, setting -2.95U/hr", 
  "COB": 28, 
  "eventualBG": 39, 
  "duration": 30, 
  "tick": -8, 
  "IOB": 1.012
}