[
  {
    "created_at": "2017-04-22T04:13:42.628Z", 
    "mmtune": {
      "scanDetails": [
        [
          "916.564", 
          5, 
          -84
        ], 
        [
          "916.588", 
          5, 
          -80
        ], 
        [
          "916.612", 
          5, 
          -80
        ], 
        [
          "916.636", 
          5, 
          -79
        ], 
        [
          "916.660", 
          5, 
          -80
        ], 
        [
          "916.684", 
          5, 
          -81
        ], 
        [
          "916.708", 
          5, 
          -90
        ]
      ], 
      "setFreq": 916.636, 
      "usedDefault": false, 
      "timestamp": "2017-04-22T04:10:59.000Z"
    }, 
    "pump": {
      "battery": {
        "status": "normal", 
        "voltage": 1.38
      }, 
      "status": {
        "status": "normal", 
        "timestamp": "2017-04-22T04:11:21.000Z", 
        "bolusing": false, 
        "suspended": false
      }, 
      "reservoir": 52.75, 
      "clock": "2017-04-21T21:11:22-07:00"
    }, 
    "openaps": {
      "suggested": {
        "bg": 70, 
        "temp": "absolute", 
        "snoozeBG": 57, 
        "timestamp": "2017-04-22T04:13:04.000Z", 
        "rate": 0.375, 
        "reason": "COB: 82, Dev: 22, BGI: -8.25, ISF: 86, Target: 80; Eventual BG 39 < 80, setting 0.375U/hr", 
        "COB": 82, 
        "eventualBG": 39, 
        "duration": 30, 
        "tick": -4, 
        "IOB": 3.342
      }, 
      "iob": {
        "netbasalinsulin": -0.05, 
        "timestamp": "2017-04-22T04:11:22.000Z", 
        "activity": 0.0191, 
        "basaliob": 0.251, 
        "hightempinsulin": 0.55, 
        "bolussnooze": 1.96, 
        "iob": 3.342
      }, 
      "enacted": {
        "bg": 70, 
        "temp": "absolute", 
        "snoozeBG": 57, 
        "recieved": true, 
        "predBGs": {
          "COB": [
            70, 
            66, 
            60, 
            53, 
            45, 
            39, 
            39, 
            39, 
            39, 
            39, 
            39, 
            39, 
            39
          ], 
          "aCOB": [
            70, 
            72, 
            72, 
            71, 
            68, 
            64, 
            59, 
            53, 
            45, 
            39, 
            39, 
            39, 
            39, 
            39, 
            39, 
            39, 
            39, 
            39, 
            39, 
            39, 
            39, 
            39, 
            39, 
            39, 
            39, 
            39, 
            39, 
            39, 
            39, 
            39, 
            42, 
            50, 
            57, 
            65, 
            73, 
            81, 
            88, 
            96, 
            103, 
            110, 
            118, 
            125, 
            132
          ], 
          "IOB": [
            70, 
            65, 
            59, 
            51, 
            42, 
            39, 
            39, 
            39, 
            39, 
            39, 
            39, 
            39, 
            39
          ]
        }, 
        "reason": "COB: 82, Dev: 22, BGI: -8.25, ISF: 86, Target: 80; Eventual BG 39 < 80, setting 0.375U/hr", 
        "rate": 0.375, 
        "COB": 82, 
        "eventualBG": 39, 
        "timestamp": "2017-04-22T04:13:26.000Z", 
        "duration": 30, 
        "tick": -4, 
        "IOB": 3.342
      }
    }, 
    "uploader": {
      "battery": 68, 
      "batteryVoltage": 3865
    }, 
    "device": "openaps://indy-e1", 
    "_id": "58fad8768b1f145d415c44d1"
  }
]