[
  {
    "created_at": "2017-04-02T22:51:32.819Z", 
    "mmtune": {
      "scanDetails": [
        [
          "916.540", 
          1, 
          -92
        ], 
        [
          "916.564", 
          5, 
          -56
        ], 
        [
          "916.588", 
          5, 
          -53
        ], 
        [
          "916.612", 
          5, 
          -52
        ], 
        [
          "916.636", 
          5, 
          -56
        ], 
        [
          "916.660", 
          5, 
          -60
        ], 
        [
          "916.684", 
          5, 
          -55
        ]
      ], 
      "setFreq": 916.612, 
      "usedDefault": false, 
      "timestamp": "2017-04-02T22:49:13.000Z"
    }, 
    "pump": {
      "battery": {
        "status": "normal", 
        "voltage": 1.47
      }, 
      "status": {
        "status": "normal", 
        "timestamp": "2017-04-02T22:49:33.000Z", 
        "bolusing": false, 
        "suspended": false
      }, 
      "reservoir": 116.85, 
      "clock": "2017-04-02T15:49:28-07:00"
    }, 
    "openaps": {
      "suggested": {
        "bg": 128, 
        "temp": "absolute", 
        "snoozeBG": 132, 
        "timestamp": "2017-04-02T22:51:17.000Z", 
        "predBGs": {
          "COB": [
            128, 
            127, 
            126, 
            126, 
            125, 
            126, 
            127, 
            128, 
            130, 
            132, 
            136, 
            139, 
            143, 
            147, 
            150, 
            154, 
            158, 
            162, 
            166, 
            170, 
            175, 
            180, 
            184, 
            189, 
            194, 
            199, 
            204, 
            209, 
            214, 
            219, 
            224, 
            229, 
            233, 
            238, 
            243, 
            248, 
            252, 
            257, 
            261, 
            266, 
            270, 
            274, 
            278
          ], 
          "aCOB": [
            128, 
            128, 
            128, 
            128, 
            129, 
            130, 
            131, 
            134, 
            136, 
            139, 
            143, 
            148, 
            152, 
            156, 
            160, 
            165, 
            169, 
            173, 
            178, 
            183, 
            188, 
            193, 
            198, 
            203, 
            208, 
            213, 
            219, 
            224, 
            229, 
            234, 
            239, 
            244, 
            249, 
            254, 
            259, 
            263, 
            268, 
            273, 
            277, 
            281, 
            285, 
            289, 
            293
          ], 
          "IOB": [
            128, 
            126, 
            124, 
            122, 
            119, 
            116, 
            113, 
            110, 
            107, 
            104, 
            101, 
            97, 
            93, 
            89, 
            86, 
            82, 
            79, 
            76, 
            73, 
            71, 
            68, 
            67, 
            65, 
            63, 
            62, 
            61, 
            60, 
            59, 
            58, 
            58, 
            57, 
            57, 
            56
          ]
        }, 
        "reason": "COB: 31, Dev: 55, BGI: -10.14, ISF: 106, Target: 104; Eventual BG 278 >= 104, temp 1.175 >~ req 1.05U/hr", 
        "COB": 31, 
        "eventualBG": 278, 
        "tick": -1, 
        "IOB": 0.962
      }, 
      "iob": {
        "netbasalinsulin": 0.55, 
        "timestamp": "2017-04-02T22:49:28.000Z", 
        "activity": 0.0192, 
        "basaliob": 0.569, 
        "hightempinsulin": 0.9, 
        "bolussnooze": 0, 
        "iob": 0.962
      }, 
      "enacted": {
        "bg": 126, 
        "temp": "absolute", 
        "snoozeBG": 139, 
        "recieved": true, 
        "reason": "COB: 32, Dev: 73, BGI: -11.46, ISF: 106, Target: 104; Eventual BG 312 >= 104, temp 0.75<1.2U/hr", 
        "rate": 1.175, 
        "COB": 32, 
        "eventualBG": 312, 
        "timestamp": "2017-04-02T22:33:59.000Z", 
        "duration": 30, 
        "tick": "+1", 
        "IOB": 1.122
      }
    }, 
    "uploader": {
      "battery": 89, 
      "batteryVoltage": 4072
    }, 
    "device": "openaps://indy-e1", 
    "_id": "58e18074f679e5760814fe4f"
  }
]