{
  "bg": 153, 
  "temp": "absolute", 
  "snoozeBG": 77, 
  "recieved": true, 
  "predBGs": {
    "aCOB": [
      153, 
      157, 
      160, 
      162, 
      163, 
      163, 
      161, 
      159, 
      155, 
      151, 
      146, 
      141, 
      137, 
      133, 
      129, 
      125, 
      122, 
      118, 
      115, 
      112, 
      110, 
      107, 
      105, 
      104, 
      102, 
      101, 
      99, 
      98, 
      97, 
      97, 
      96, 
      96, 
      95
    ], 
    "IOB": [
      153, 
      148, 
      143, 
      138, 
      134, 
      129, 
      124, 
      118, 
      114, 
      109, 
      104, 
      100, 
      95, 
      91, 
      87, 
      83, 
      80, 
      76, 
      73, 
      70, 
      68, 
      66, 
      64, 
      62, 
      60, 
      59, 
      57, 
      56, 
      56, 
      55, 
      54, 
      54, 
      53
    ]
  }, 
  "reason": "COB: 6, Dev: 1, BGI: -2.44, ISF: 89, Target: 97; Eventual BG 75 < 97, setting -0.25U/hr", 
  "rate": 0.0, 
  "COB": 6, 
  "eventualBG": 75, 
  "timestamp": "2017-04-27T11:44:31.994033", 
  "duration": 30, 
  "tick": -5, 
  "IOB": 0.89
}