{
  "bg": 124, 
  "temp": "absolute", 
  "snoozeBG": 92, 
  "recieved": true, 
  "predBGs": {
    "COB": [
      124, 
      120, 
      116, 
      112, 
      109, 
      106, 
      103, 
      100, 
      98, 
      96, 
      95, 
      94, 
      93, 
      92, 
      92, 
      92, 
      92, 
      92, 
      92, 
      93, 
      94, 
      95, 
      95, 
      96, 
      97, 
      98, 
      100, 
      101, 
      102, 
      103, 
      105, 
      106, 
      107, 
      108, 
      109, 
      110, 
      111, 
      112, 
      112, 
      113, 
      114, 
      114, 
      115
    ], 
    "aCOB": [
      124, 
      128, 
      132, 
      136, 
      139, 
      141, 
      143, 
      145, 
      146, 
      147, 
      148, 
      149, 
      148, 
      148, 
      147, 
      146, 
      145, 
      145, 
      144, 
      144, 
      144, 
      144, 
      144, 
      144, 
      145, 
      145, 
      145, 
      146, 
      146, 
      147, 
      147, 
      148, 
      148, 
      148, 
      149
    ], 
    "IOB": [
      124, 
      120, 
      116, 
      112, 
      108, 
      105, 
      101, 
      98, 
      96, 
      93, 
      91, 
      89, 
      88, 
      86, 
      85, 
      84, 
      83, 
      83, 
      82, 
      82, 
      82, 
      82, 
      82, 
      82, 
      82, 
      83, 
      83, 
      84, 
      84, 
      85, 
      85, 
      86, 
      86, 
      86, 
      87
    ]
  }, 
  "reason": "COB: 6, Dev: 5, BGI: -4.88, ISF: 86, Target: 96; Eventual BG 115 > 96 but Min. Delta -4.00 < Exp. Delta -3.5; setting current basal of 0.7 as temp", 
  "rate": 0.675, 
  "COB": 6, 
  "eventualBG": 115, 
  "timestamp": "2017-04-07T09:08:59.103469", 
  "duration": 30, 
  "tick": -4, 
  "IOB": 0.673
}