[
  {
    "trend_arrow": "FLAT", 
    "display_time": "2017-04-02T07:10:42-07:00", 
    "noise": 1, 
    "direction": "Flat", 
    "system_time": "2017-04-02T14:09:42-07:00", 
    "sgv": 90, 
    "dateString": "2017-04-02T07:10:42-07:00", 
    "device": "openaps://indy-e1/cgm", 
    "unfiltered": 96768, 
    "rssi": 187, 
    "date": 1491142242000.0, 
    "filtered": 93248, 
    "type": "sgv", 
    "glucose": 90
  }, 
  {
    "trend_arrow": "FLAT", 
    "display_time": "2017-04-02T07:05:42-07:00", 
    "noise": 1, 
    "direction": "Flat", 
    "system_time": "2017-04-02T14:04:42-07:00", 
    "sgv": 87, 
    "dateString": "2017-04-02T07:05:42-07:00", 
    "device": "openaps://indy-e1/cgm", 
    "unfiltered": 94864, 
    "rssi": 187, 
    "date": 1491141942000.0, 
    "filtered": 91904, 
    "type": "sgv", 
    "glucose": 87
  }, 
  {
    "trend_arrow": "FLAT", 
    "display_time": "2017-04-02T07:00:42-07:00", 
    "noise": 1, 
    "direction": "Flat", 
    "system_time": "2017-04-02T13:59:42-07:00", 
    "sgv": 84, 
    "dateString": "2017-04-02T07:00:42-07:00", 
    "device": "openaps://indy-e1/cgm", 
    "unfiltered": 92144, 
    "rssi": 187, 
    "date": 1491141642000.0, 
    "filtered": 91264, 
    "type": "sgv", 
    "glucose": 84
  }, 
  {
    "trend_arrow": "FLAT", 
    "display_time": "2017-04-02T06:55:42-07:00", 
    "noise": 1, 
    "direction": "Flat", 
    "system_time": "2017-04-02T13:54:42-07:00", 
    "sgv": 83, 
    "dateString": "2017-04-02T06:55:42-07:00", 
    "device": "openaps://indy-e1/cgm", 
    "unfiltered": 91248, 
    "rssi": 187, 
    "date": 1491141342000.0, 
    "filtered": 91136, 
    "type": "sgv", 
    "glucose": 83
  }, 
  {
    "trend_arrow": "FLAT", 
    "display_time": "2017-04-02T06:50:42-07:00", 
    "noise": 1, 
    "direction": "Flat", 
    "system_time": "2017-04-02T13:49:42-07:00", 
    "sgv": 83, 
    "dateString": "2017-04-02T06:50:42-07:00", 
    "device": "openaps://indy-e1/cgm", 
    "unfiltered": 91296, 
    "rssi": 187, 
    "date": 1491141042000.0, 
    "filtered": 91536, 
    "type": "sgv", 
    "glucose": 83
  }, 
  {
    "trend_arrow": "FLAT", 
    "display_time": "2017-04-02T06:45:42-07:00", 
    "noise": 1, 
    "direction": "Flat", 
    "system_time": "2017-04-02T13:44:42-07:00", 
    "sgv": 83, 
    "dateString": "2017-04-02T06:45:42-07:00", 
    "device": "openaps://indy-e1/cgm", 
    "unfiltered": 91664, 
    "rssi": 187, 
    "date": 1491140742000.0, 
    "filtered": 92736, 
    "type": "sgv", 
    "glucose": 83
  }
]