[
  {
    "trend_arrow": "45_DOWN", 
    "display_time": "2017-04-26T07:29:32-07:00", 
    "noise": 1, 
    "direction": "FortyFiveDown", 
    "system_time": "2017-04-26T14:12:49-07:00", 
    "sgv": 70, 
    "dateString": "2017-04-26T07:29:32-07:00", 
    "device": "openaps://indy-e1/cgm", 
    "unfiltered": 89792, 
    "rssi": 201, 
    "date": 1493216972000.0, 
    "filtered": 93792, 
    "type": "sgv", 
    "glucose": 70
  }, 
  {
    "trend_arrow": "45_DOWN", 
    "display_time": "2017-04-26T07:24:32-07:00", 
    "noise": 1, 
    "direction": "FortyFiveDown", 
    "system_time": "2017-04-26T14:07:49-07:00", 
    "sgv": 73, 
    "dateString": "2017-04-26T07:24:32-07:00", 
    "device": "openaps://indy-e1/cgm", 
    "unfiltered": 92048, 
    "rssi": 212, 
    "date": 1493216672000.0, 
    "filtered": 99248, 
    "type": "sgv", 
    "glucose": 73
  }, 
  {
    "trend_arrow": "SINGLE_DOWN", 
    "display_time": "2017-04-26T07:19:32-07:00", 
    "noise": 1, 
    "direction": "SingleDown", 
    "system_time": "2017-04-26T14:02:49-07:00", 
    "sgv": 79, 
    "dateString": "2017-04-26T07:19:32-07:00", 
    "device": "openaps://indy-e1/cgm", 
    "unfiltered": 96176, 
    "rssi": 216, 
    "date": 1493216372000.0, 
    "filtered": 106624, 
    "type": "sgv", 
    "glucose": 79
  }, 
  {
    "trend_arrow": "SINGLE_DOWN", 
    "display_time": "2017-04-26T07:14:32-07:00", 
    "noise": 1, 
    "direction": "SingleDown", 
    "system_time": "2017-04-26T13:57:49-07:00", 
    "sgv": 88, 
    "dateString": "2017-04-26T07:14:32-07:00", 
    "device": "openaps://indy-e1/cgm", 
    "unfiltered": 102096, 
    "rssi": 215, 
    "date": 1493216072000.0, 
    "filtered": 114896, 
    "type": "sgv", 
    "glucose": 88
  }, 
  {
    "trend_arrow": "SINGLE_DOWN", 
    "display_time": "2017-04-26T07:09:32-07:00", 
    "noise": 1, 
    "direction": "SingleDown", 
    "system_time": "2017-04-26T13:52:49-07:00", 
    "sgv": 98, 
    "dateString": "2017-04-26T07:09:32-07:00", 
    "device": "openaps://indy-e1/cgm", 
    "unfiltered": 109120, 
    "rssi": 203, 
    "date": 1493215772000.0, 
    "filtered": 122848, 
    "type": "sgv", 
    "glucose": 98
  }, 
  {
    "trend_arrow": "45_DOWN", 
    "display_time": "2017-04-26T07:04:32-07:00", 
    "noise": 1, 
    "direction": "FortyFiveDown", 
    "system_time": "2017-04-26T13:47:49-07:00", 
    "sgv": 112, 
    "dateString": "2017-04-26T07:04:32-07:00", 
    "device": "openaps://indy-e1/cgm", 
    "unfiltered": 119024, 
    "rssi": 198, 
    "date": 1493215472000.0, 
    "filtered": 129728, 
    "type": "sgv", 
    "glucose": 112
  }
]