[
  {
    "trend_arrow": "FLAT", 
    "display_time": "2017-04-19T19:49:20-07:00", 
    "noise": 1, 
    "direction": "Flat", 
    "system_time": "2017-04-20T02:48:15-07:00", 
    "sgv": 67, 
    "dateString": "2017-04-19T19:49:20-07:00", 
    "device": "openaps://indy-e1/cgm", 
    "unfiltered": 83776, 
    "rssi": 193, 
    "date": 1492656560000.0, 
    "filtered": 75984, 
    "type": "sgv", 
    "glucose": 67
  }, 
  {
    "trend_arrow": "FLAT", 
    "display_time": "2017-04-19T19:44:20-07:00", 
    "noise": 1, 
    "direction": "Flat", 
    "system_time": "2017-04-20T02:43:15-07:00", 
    "sgv": 59, 
    "dateString": "2017-04-19T19:44:20-07:00", 
    "device": "openaps://indy-e1/cgm", 
    "unfiltered": 76928, 
    "rssi": 198, 
    "date": 1492656260000.0, 
    "filtered": 77424, 
    "type": "sgv", 
    "glucose": 59
  }, 
  {
    "trend_arrow": "45_DOWN", 
    "display_time": "2017-04-19T19:39:20-07:00", 
    "noise": 1, 
    "direction": "FortyFiveDown", 
    "system_time": "2017-04-20T02:38:15-07:00", 
    "sgv": 57, 
    "dateString": "2017-04-19T19:39:20-07:00", 
    "device": "openaps://indy-e1/cgm", 
    "unfiltered": 75024, 
    "rssi": 193, 
    "date": 1492655960000.0, 
    "filtered": 82032, 
    "type": "sgv", 
    "glucose": 57
  }, 
  {
    "trend_arrow": "45_DOWN", 
    "display_time": "2017-04-19T19:34:20-07:00", 
    "noise": 1, 
    "direction": "FortyFiveDown", 
    "system_time": "2017-04-20T02:33:16-07:00", 
    "sgv": 61, 
    "dateString": "2017-04-19T19:34:20-07:00", 
    "device": "openaps://indy-e1/cgm", 
    "unfiltered": 78464, 
    "rssi": 426, 
    "date": 1492655660000.0, 
    "filtered": 87824, 
    "type": "sgv", 
    "glucose": 61
  }, 
  {
    "trend_arrow": "45_DOWN", 
    "display_time": "2017-04-19T19:29:20-07:00", 
    "noise": 1, 
    "direction": "FortyFiveDown", 
    "system_time": "2017-04-20T02:28:15-07:00", 
    "sgv": 67, 
    "dateString": "2017-04-19T19:29:20-07:00", 
    "device": "openaps://indy-e1/cgm", 
    "unfiltered": 83680, 
    "rssi": 183, 
    "date": 1492655360000.0, 
    "filtered": 93520, 
    "type": "sgv", 
    "glucose": 67
  }, 
  {
    "trend_arrow": "45_DOWN", 
    "display_time": "2017-04-19T19:24:20-07:00", 
    "noise": 1, 
    "direction": "FortyFiveDown", 
    "system_time": "2017-04-20T02:23:15-07:00", 
    "sgv": 77, 
    "dateString": "2017-04-19T19:24:20-07:00", 
    "device": "openaps://indy-e1/cgm", 
    "unfiltered": 91344, 
    "rssi": 179, 
    "date": 1492655060000.0, 
    "filtered": 98928, 
    "type": "sgv", 
    "glucose": 77
  }
]