{
  "device": "openaps://indy-e1", 
  "pump": {
    "battery": {
      "status": "normal", 
      "voltage": 1.41
    }, 
    "status": {
      "status": "normal", 
      "timestamp": "2017-04-10T00:17:29.000Z", 
      "bolusing": false, 
      "suspended": false
    }, 
    "reservoir": 43.975, 
    "clock": "2017-04-09T17:17:26-07:00"
  }, 
  "uploader": {
    "battery": 100, 
    "batteryVoltage": 4377
  }, 
  "openaps": {
    "suggested": {
      "bg": 55, 
      "temp": "absolute", 
      "snoozeBG": 36, 
      "timestamp": "2017-04-10T00:19:15.000Z", 
      "predBGs": {
        "aCOB": [
          55, 
          58, 
          61, 
          64, 
          68, 
          71, 
          75, 
          79, 
          83, 
          88, 
          92, 
          97, 
          102, 
          106, 
          110, 
          114, 
          117, 
          120, 
          122, 
          124, 
          126, 
          128, 
          130, 
          132, 
          133, 
          135, 
          136, 
          138, 
          139, 
          140, 
          140, 
          141, 
          142, 
          142, 
          143
        ], 
        "IOB": [
          55, 
          49, 
          43, 
          39, 
          39, 
          39, 
          39, 
          39, 
          39, 
          39, 
          39, 
          39, 
          39, 
          39, 
          39, 
          39, 
          39, 
          39, 
          39, 
          40, 
          42, 
          44, 
          46, 
          48, 
          49, 
          51, 
          52, 
          53, 
          55, 
          56, 
          56, 
          57, 
          58, 
          58, 
          58, 
          59
        ]
      }, 
      "reason": "COB: 9, Dev: -38, BGI: -0.09, ISF: 95, Target: 100; BG 55<75, but 26m left and 0 ~ req 0U/hr: no action required", 
      "COB": 9, 
      "eventualBG": 36, 
      "tick": -7, 
      "IOB": -0.195
    }, 
    "iob": {
      "netbasalinsulin": -0.2, 
      "timestamp": "2017-04-10T00:17:26.000Z", 
      "activity": 0.0002, 
      "basaliob": -0.195, 
      "hightempinsulin": 0.45, 
      "bolussnooze": 0, 
      "iob": -0.195
    }, 
    "enacted": {
      "bg": 62, 
      "temp": "absolute", 
      "snoozeBG": 47, 
      "recieved": true, 
      "rate": 0, 
      "reason": "COB: 9, Dev: -29, BGI: -0.14, ISF: 95, Target: 100; BG 62<75", 
      "COB": 9, 
      "eventualBG": 47, 
      "timestamp": "2017-04-10T00:13:31.000Z", 
      "duration": 30, 
      "tick": -6, 
      "IOB": -0.143
    }
  }, 
  "mmtune": {
    "scanDetails": [
      [
        "916.612", 
        4, 
        -70
      ], 
      [
        "916.636", 
        5, 
        -77
      ], 
      [
        "916.660", 
        4, 
        -92
      ], 
      [
        "916.684", 
        5, 
        -87
      ], 
      [
        "916.708", 
        3, 
        -90
      ]
    ], 
    "setFreq": 916.636, 
    "timestamp": "2017-04-10T00:17:08.000Z", 
    "usedDefault": false
  }
}