{
  "device": "openaps://indy-e1", 
  "pump": {
    "battery": {
      "status": "normal", 
      "voltage": 1.51
    }, 
    "status": {
      "status": "normal", 
      "timestamp": "2017-04-23T03:57:31.000Z", 
      "bolusing": false, 
      "suspended": false
    }, 
    "reservoir": 22.925, 
    "clock": "2017-04-22T20:57:33-07:00"
  }, 
  "uploader": {
    "battery": 66, 
    "batteryVoltage": 3841
  }, 
  "openaps": {
    "suggested": {
      "bg": 125, 
      "temp": "absolute", 
      "snoozeBG": 212, 
      "timestamp": "2017-04-23T03:59:13.000Z", 
      "reason": "COB: 43, Dev: 7, BGI: -1.87, ISF: 96, Target: 80; Eventual BG 52 < 80, bolus snooze: eventual BG range 52-212; setting current basal of 0.9 as temp. Setting neutral temp basal of 0.9U/hr", 
      "rate": 0.9, 
      "COB": 43, 
      "eventualBG": 52, 
      "duration": 30, 
      "tick": -3, 
      "IOB": 2.418
    }, 
    "iob": {
      "netbasalinsulin": -0.25, 
      "timestamp": "2017-04-23T03:57:33.000Z", 
      "activity": 0.0039, 
      "basaliob": 0.011, 
      "hightempinsulin": 0.55, 
      "bolussnooze": 2.165, 
      "iob": 2.418
    }, 
    "enacted": {
      "bg": 125, 
      "temp": "absolute", 
      "snoozeBG": 212, 
      "recieved": true, 
      "predBGs": {
        "COB": [
          125, 
          127, 
          128, 
          128, 
          127, 
          125, 
          122, 
          118, 
          112, 
          106, 
          99, 
          90, 
          81, 
          72, 
          64, 
          56, 
          49, 
          43, 
          39, 
          39, 
          39, 
          39, 
          39, 
          39, 
          39, 
          39, 
          39, 
          39, 
          39, 
          39, 
          39, 
          39, 
          39, 
          39, 
          39, 
          39, 
          39, 
          39, 
          39, 
          42, 
          45, 
          48, 
          52
        ], 
        "aCOB": [
          125, 
          133, 
          140, 
          146, 
          150, 
          153, 
          156, 
          157, 
          157, 
          156, 
          153, 
          150, 
          146, 
          141, 
          138, 
          135, 
          132, 
          130, 
          128, 
          127, 
          126, 
          126, 
          126, 
          127, 
          128, 
          130, 
          133, 
          135, 
          139, 
          143, 
          148, 
          153, 
          159, 
          165, 
          171, 
          177, 
          183, 
          189, 
          194, 
          200, 
          205, 
          210, 
          215
        ], 
        "IOB": [
          125, 
          127, 
          127, 
          126, 
          124, 
          120, 
          115, 
          109, 
          101, 
          92, 
          81, 
          70, 
          57, 
          44, 
          39
        ]
      }, 
      "rate": 0.9, 
      "reason": "COB: 43, Dev: 7, BGI: -1.87, ISF: 96, Target: 80; Eventual BG 52 < 80, bolus snooze: eventual BG range 52-212; setting current basal of 0.9 as temp. Setting neutral temp basal of 0.9U/hr", 
      "COB": 43, 
      "eventualBG": 52, 
      "timestamp": "2017-04-23T03:59:33.000Z", 
      "duration": 30, 
      "tick": -3, 
      "IOB": 2.418
    }
  }, 
  "mmtune": {
    "scanDetails": [
      [
        "916.540", 
        1, 
        -98
      ], 
      [
        "916.564", 
        5, 
        -81
      ], 
      [
        "916.588", 
        5, 
        -79
      ], 
      [
        "916.612", 
        5, 
        -79
      ], 
      [
        "916.636", 
        5, 
        -81
      ], 
      [
        "916.660", 
        5, 
        -81
      ], 
      [
        "916.684", 
        5, 
        -84
      ]
    ], 
    "setFreq": 916.612, 
    "timestamp": "2017-04-23T03:57:11.000Z", 
    "usedDefault": false
  }
}