{
  "device": "openaps://indy-e1", 
  "pump": {
    "battery": {
      "status": "normal", 
      "voltage": 1.36
    }, 
    "status": {
      "status": "normal", 
      "timestamp": "2017-04-10T18:45:20.000Z", 
      "bolusing": false, 
      "suspended": false
    }, 
    "reservoir": 20, 
    "clock": "2017-04-10T11:45:17-07:00"
  }, 
  "uploader": {
    "battery": 58, 
    "batteryVoltage": 3761
  }, 
  "openaps": {
    "suggested": {
      "bg": 117, 
      "temp": "absolute", 
      "snoozeBG": 117, 
      "timestamp": "2017-04-10T18:47:06.000Z", 
      "predBGs": {
        "COB": [
          117, 
          115, 
          114, 
          113, 
          112, 
          112, 
          113, 
          114, 
          115, 
          117, 
          120, 
          123, 
          126, 
          130, 
          134, 
          138, 
          142, 
          146, 
          150, 
          154, 
          158, 
          162, 
          166, 
          171, 
          175, 
          180, 
          184, 
          189, 
          194, 
          198, 
          203, 
          208, 
          212, 
          217, 
          222, 
          227, 
          231, 
          236, 
          241, 
          245, 
          250, 
          254, 
          259
        ], 
        "aCOB": [
          117, 
          119, 
          122, 
          125, 
          128, 
          132, 
          136, 
          140, 
          145, 
          151, 
          156, 
          163, 
          169, 
          176, 
          183, 
          190, 
          197, 
          204, 
          211, 
          218, 
          225, 
          232, 
          239, 
          245, 
          252, 
          259, 
          266, 
          273, 
          280, 
          287, 
          294, 
          301, 
          307, 
          314, 
          321, 
          327, 
          334, 
          340, 
          346, 
          352, 
          358, 
          364, 
          370
        ], 
        "IOB": [
          117, 
          115, 
          112, 
          110, 
          108, 
          105, 
          103, 
          101, 
          99, 
          96, 
          94, 
          92, 
          90, 
          88, 
          86, 
          85, 
          83, 
          82, 
          81, 
          79, 
          78, 
          77, 
          76, 
          76, 
          75, 
          74, 
          74, 
          73, 
          73, 
          73, 
          72
        ]
      }, 
      "reason": "COB: 58, Dev: 36, BGI: -7.79, ISF: 95, Target: 100; Eventual BG 259 >= 100, temp 0.75<0.85U/hr, but 21m left and 0.75 ~ req 0.85U/hr: no action required", 
      "COB": 58, 
      "eventualBG": 259, 
      "tick": "+0", 
      "IOB": 0.691
    }, 
    "iob": {
      "netbasalinsulin": 0.65, 
      "timestamp": "2017-04-10T18:45:17.000Z", 
      "activity": 0.0164, 
      "basaliob": 0.355, 
      "hightempinsulin": 0.95, 
      "bolussnooze": 0, 
      "iob": 0.691
    }, 
    "enacted": {
      "bg": 120, 
      "temp": "absolute", 
      "snoozeBG": 110, 
      "recieved": true, 
      "rate": 0.75, 
      "reason": "COB: 59, Dev: 35, BGI: -8.69, ISF: 95, Target: 100; Eventual BG 248 >= 100, temp 0.575<0.75U/hr", 
      "COB": 59, 
      "eventualBG": 248, 
      "timestamp": "2017-04-10T18:36:36.000Z", 
      "duration": 30, 
      "tick": -2, 
      "IOB": 0.82
    }
  }, 
  "mmtune": {
    "scanDetails": [
      [
        "916.540", 
        5, 
        -77
      ], 
      [
        "916.564", 
        5, 
        -63
      ], 
      [
        "916.588", 
        3, 
        -76
      ], 
      [
        "916.612", 
        5, 
        -71
      ], 
      [
        "916.636", 
        5, 
        -81
      ], 
      [
        "916.660", 
        4, 
        -90
      ], 
      [
        "916.684", 
        5, 
        -82
      ]
    ], 
    "setFreq": 916.564, 
    "timestamp": "2017-04-10T18:44:59.000Z", 
    "usedDefault": false
  }
}