{
  "device": "openaps://indy-e1", 
  "pump": {
    "battery": {
      "status": "normal", 
      "voltage": 1.55
    }, 
    "status": {
      "status": "normal", 
      "timestamp": "2017-04-12T00:00:30.000Z", 
      "bolusing": false, 
      "suspended": false
    }, 
    "reservoir": 101.375, 
    "clock": "2017-04-11T17:00:28-07:00"
  }, 
  "uploader": {
    "battery": 47, 
    "batteryVoltage": 3662
  }, 
  "openaps": {
    "suggested": {
      "bg": 85, 
      "temp": "absolute", 
      "snoozeBG": 129, 
      "timestamp": "2017-04-12T00:02:16.000Z", 
      "reason": "COB: 58, Dev: 21, BGI: -4.4, ISF: 101, Target: 80; Eventual BG 41 < 80, bolus snooze: eventual BG range 41-129; setting current basal of 0.575 as temp", 
      "rate": 0.575, 
      "COB": 58, 
      "eventualBG": 41, 
      "duration": 30, 
      "tick": "+2", 
      "IOB": 1.941
    }, 
    "iob": {
      "netbasalinsulin": 0, 
      "timestamp": "2017-04-12T00:00:28.000Z", 
      "activity": 0.0087, 
      "basaliob": 0.09, 
      "hightempinsulin": 0.45, 
      "bolussnooze": 1.447, 
      "iob": 1.941
    }, 
    "enacted": {
      "bg": 85, 
      "temp": "absolute", 
      "snoozeBG": 129, 
      "recieved": true, 
      "predBGs": {
        "COB": [
          85, 
          85, 
          83, 
          81, 
          78, 
          74, 
          69, 
          63, 
          57, 
          50, 
          42, 
          39, 
          39, 
          39, 
          39, 
          39, 
          39, 
          39, 
          39, 
          39, 
          39, 
          39, 
          39, 
          39, 
          39, 
          39, 
          39, 
          39, 
          39, 
          39, 
          39, 
          39, 
          39, 
          39, 
          39, 
          39, 
          39, 
          39, 
          39, 
          39, 
          39, 
          39, 
          41
        ], 
        "aCOB": [
          85, 
          91, 
          95, 
          99, 
          101, 
          103, 
          104, 
          103, 
          103, 
          101, 
          99, 
          96, 
          95, 
          94, 
          93, 
          92, 
          93, 
          93, 
          94, 
          96, 
          98, 
          101, 
          104, 
          107, 
          111, 
          116, 
          121, 
          127, 
          133, 
          140, 
          146, 
          154, 
          161, 
          169, 
          176, 
          183, 
          190, 
          197, 
          204, 
          211, 
          217, 
          224, 
          231
        ], 
        "IOB": [
          85, 
          84, 
          82, 
          79, 
          75, 
          69, 
          62, 
          54, 
          46, 
          39, 
          39, 
          39, 
          39
        ]
      }, 
      "rate": 0.55, 
      "reason": "COB: 58, Dev: 21, BGI: -4.4, ISF: 101, Target: 80; Eventual BG 41 < 80, bolus snooze: eventual BG range 41-129; setting current basal of 0.575 as temp", 
      "COB": 58, 
      "eventualBG": 41, 
      "timestamp": "2017-04-12T00:02:36.000Z", 
      "duration": 30, 
      "tick": "+2", 
      "IOB": 1.941
    }
  }, 
  "mmtune": {
    "scanDetails": [
      [
        "916.540", 
        4, 
        -85
      ], 
      [
        "916.564", 
        5, 
        -68
      ], 
      [
        "916.588", 
        5, 
        -69
      ], 
      [
        "916.612", 
        5, 
        -69
      ], 
      [
        "916.636", 
        5, 
        -70
      ], 
      [
        "916.660", 
        5, 
        -65
      ], 
      [
        "916.684", 
        5, 
        -72
      ]
    ], 
    "setFreq": 916.66, 
    "timestamp": "2017-04-12T00:00:10.000Z", 
    "usedDefault": false
  }
}